parserconfig/__init__.py
parserconfig/parserconfig.py
parserconfig-1.0.0.dist-info/LICENSE
parserconfig-1.0.0.dist-info/METADATA
parserconfig-1.0.0.dist-info/WHEEL
parserconfig-1.0.0.dist-info/top_level.txt
parserconfig-1.0.0.dist-info/RECORD
