Metadata-Version: 2.1
Name: parserconfig
Version: 1.0.0
Summary: Plug-n-Play ConfigParser for extensible use cases.
Home-page: https://github.com/Fauxsys/parserconfig.git
Author: Steven Cassamajor
Author-email: contributor@networkaxis.org
License: UNKNOWN
Platform: UNKNOWN
Classifier: Programming Language :: Python :: 3
Requires-Python: >=3.7
License-File: LICENSE
Provides-Extra: test
Requires-Dist: pytest ; extra == 'test'
Requires-Dist: pytest-cov ; extra == 'test'
Requires-Dist: tox ; extra == 'test'
